Examples/__init__.py
RFEM/__init__.py
RFEM/baseData.py
RFEM/baseSettings.py
RFEM/connectionGlobals.py
RFEM/dataTypes.py
RFEM/dependencies.py
RFEM/enums.py
RFEM/formula.py
RFEM/globalParameter.py
RFEM/initModel.py
RFEM/suds_requests.py
RFEM/AluminumDesign/__init__.py
RFEM/AluminumDesign/aluminumSLSConfiguration.py
RFEM/AluminumDesign/aluminumULSConfiguration.py
RFEM/BasicObjects/__init__.py
RFEM/BasicObjects/bracing.py
RFEM/BasicObjects/frame.py
RFEM/BasicObjects/line.py
RFEM/BasicObjects/lineSet.py
RFEM/BasicObjects/material.py
RFEM/BasicObjects/member.py
RFEM/BasicObjects/memberSet.py
RFEM/BasicObjects/node.py
RFEM/BasicObjects/opening.py
RFEM/BasicObjects/section.py
RFEM/BasicObjects/solid.py
RFEM/BasicObjects/solidSet.py
RFEM/BasicObjects/surface.py
RFEM/BasicObjects/surfaceSet.py
RFEM/BasicObjects/thickness.py
RFEM/Calculate/__init__.py
RFEM/Calculate/meshSettings.py
RFEM/Calculate/optimizationSettings.py
RFEM/ConcreteDesign/ConcreteServiceabilityConfigurations.py
RFEM/ConcreteDesign/ConcreteUltimateConfigurations.py
RFEM/ConcreteDesign/__init__.py
RFEM/DynamicLoads/__init__.py
RFEM/DynamicLoads/responseSpectrum.py
RFEM/GuideObjects/__init__.py
RFEM/GuideObjects/coordinateSystem.py
RFEM/GuideObjects/note.py
RFEM/Imperfections/__init__.py
RFEM/Imperfections/imperfectionCase.py
RFEM/Imperfections/memberImperfection.py
RFEM/Imperfections/membersetImperfection.py
RFEM/ImportExport/__init__.py
RFEM/ImportExport/exports.py
RFEM/ImportExport/imports.py
RFEM/LoadCasesAndCombinations/__init__.py
RFEM/LoadCasesAndCombinations/action.py
RFEM/LoadCasesAndCombinations/actionCombination.py
RFEM/LoadCasesAndCombinations/combinationWizard.py
RFEM/LoadCasesAndCombinations/designSituation.py
RFEM/LoadCasesAndCombinations/loadCase.py
RFEM/LoadCasesAndCombinations/loadCasesAndCombinations.py
RFEM/LoadCasesAndCombinations/loadCombination.py
RFEM/LoadCasesAndCombinations/modalAnalysisSettings.py
RFEM/LoadCasesAndCombinations/resultCombination.py
rfem-1.20.5.dist-info/licenses/LICENSE
rfem-1.20.5.dist-info/METADATA
rfem-1.20.5.dist-info/WHEEL
rfem-1.20.5.dist-info/top_level.txt
rfem-1.20.5.dist-info/RECORD
