Metadata-Version: 2.4
Name: RFEM
Version: 1.20.5
Summary: Python Framework for RFEM6 Web Services
Home-page: https://github.com/Dlubal-Software/RFEM_Python_Client
Author: Dlubal Software
Author-email: info@dlubal.com
License: MIT
Classifier: License :: OSI Approved :: MIT License
Classifier: Programming Language :: Python :: 3
Classifier: Programming Language :: Python :: 3.10
Classifier: Programming Language :: Python :: 3.11
License-File: LICENSE
Requires-Dist: requests
Requires-Dist: six
Requires-Dist: suds-py3
Requires-Dist: xmltodict
Requires-Dist: pytest
Requires-Dist: mock
Requires-Dist: setuptools
Dynamic: author
Dynamic: author-email
Dynamic: classifier
Dynamic: description
Dynamic: description-content-type
Dynamic: home-page
Dynamic: license
Dynamic: license-file
Dynamic: requires-dist
Dynamic: summary
